calico_lib/__init__.py
calico_lib/cli.py
calico_lib/config.py
calico_lib/contest.py
calico_lib/judge_api.py
calico_lib/legacy.py
calico_lib/multicase.py
calico_lib/problem.py
calico_lib/runner.py
calico_lib-0.1.20.dist-info/licenses/LICENSE
calico_lib-0.1.20.dist-info/WHEEL
calico_lib-0.1.20.dist-info/METADATA
calico_lib-0.1.20.dist-info/RECORD
