Metadata-Version: 2.4
Name: calico_lib
Version: 0.1.20
Summary: CALICO lib for all your problem writing needs
Author-email: Connor Chang <connorc0627@gmail.com>
Classifier: License :: OSI Approved :: MIT License
License-File: LICENSE
Requires-Dist: requests
Project-URL: Home, https://github.com/calico-team/CALICOlib
